[
  {
    "id": 1,
    "title": "Sentosa Island Adventure",
    "slug": "sentosa-island-adventure",
    "description": "Enjoy fun rides, beaches, and attractions at Sentosa Island. Perfect for families, friends, and solo travelers.",
    "mainImage": "/images/img1.jpg",
    "gallery": ["/images/img1.jpg","/images/img2.jpg","/images/img3.jpg"],
    "duration": "1 Day",
    "price": 100,
    "category": "Adventure",
    "highlights": ["Universal Studios Singapore","S.E.A. Aquarium","Adventure Cove Waterpark"],
    "itinerary":[{"time":"09:00 AM","activity":"Pick-up from hotel"},{"time":"10:00 AM","activity":"Universal Studios Singapore entry"},{"time":"01:00 PM","activity":"Lunch at Sentosa"},{"time":"03:00 PM","activity":"S.E.A. Aquarium visit"},{"time":"05:00 PM","activity":"Return to hotel"}],
    "inclusions":["Hotel Pickup & Drop","Entry Tickets","Lunch"],
    "exclusions":["Personal Expenses","Optional Rides"],
    "rating": 4.5,
    "reviews":[{"name":"Ali Khan","rating":5,"comment":"Amazing experience! Kids loved it."},{"name":"Sara Lim","rating":4,"comment":"Great tour, well organized."}],
    "contactInfo":{"phone":"+65 1234 5678","email":"info@singtours.com"}
  },
  {
    "id": 2,
    "title": "Gardens by the Bay Tour",
    "slug": "gardens-by-the-bay",
    "description": "Explore the futuristic gardens, Flower Dome, Cloud Forest, and Supertree Grove.",
    "mainImage": "/images/img2.jpg",
    "gallery": ["/images/img1.jpg","/images/img2.jpg","/images/img3.jpg"],
    "duration": "Half Day",
    "price": 60,
    "category": "Nature",
    "highlights": ["Flower Dome","Cloud Forest","Supertree Grove"],
    "itinerary":[{"time":"09:00 AM","activity":"Hotel Pickup"},{"time":"09:30 AM","activity":"Gardens by the Bay visit"},{"time":"12:00 PM","activity":"Return to hotel"}],
    "inclusions":["Hotel Pickup & Drop","Entry Tickets"],
    "exclusions":["Meals","Personal Expenses"],
    "rating": 4.7,
    "reviews":[{"name":"John Doe","rating":5,"comment":"Beautiful gardens and amazing structures."},{"name":"Mary Tan","rating":4,"comment":"Loved the Cloud Forest."}],
    "contactInfo":{"phone":"+65 9876 5432","email":"info@singtours.com"}
  },
  {
    "id": 3,
    "title": "Singapore City Highlights",
    "slug": "singapore-city-highlights",
    "description": "Visit Marina Bay Sands, Merlion Park, Chinatown, and Little India.",
    "mainImage": "/images/img3.jpg",
    "gallery": ["/images/img1.jpg","/images/img2.jpg","/images/img3.jpg"],
    "duration": "Full Day",
    "price": 80,
    "category": "City Tour",
    "highlights": ["Marina Bay Sands","Merlion Park","Chinatown","Little India"],
    "itinerary":[{"time":"08:30 AM","activity":"Hotel Pickup"},{"time":"09:00 AM","activity":"Marina Bay Sands"},{"time":"11:00 AM","activity":"Merlion Park"},{"time":"01:00 PM","activity":"Lunch"},{"time":"02:00 PM","activity":"Chinatown & Little India"},{"time":"06:00 PM","activity":"Return to hotel"}],
    "inclusions":["Hotel Pickup & Drop","Lunch","Guide"],
    "exclusions":["Optional shopping","Personal Expenses"],
    "rating": 4.6,
    "reviews":[{"name":"Liam Wong","rating":5,"comment":"City tour was very informative."},{"name":"Emily Ng","rating":4,"comment":"Great guide, enjoyed every stop."}],
    "contactInfo":{"phone":"+65 1122 3344","email":"info@singtours.com"}
  },
  {
    "id": 4,
    "title": "Singapore Night Safari",
    "slug": "singapore-night-safari",
    "description": "Experience the world’s first nocturnal wildlife park with tram rides and walking trails.",
    "mainImage": "/images/img1.jpg",
    "gallery": ["/images/img1.jpg","/images/img2.jpg","/images/img3.jpg"],
    "duration": "Evening",
    "price": 70,
    "category": "Wildlife",
    "highlights": ["Tram Safari","Walking Trails","Animal Shows"],
    "itinerary":[{"time":"06:00 PM","activity":"Hotel Pickup"},{"time":"07:00 PM","activity":"Night Safari Tram"},{"time":"09:00 PM","activity":"Walking Trails"},{"time":"10:00 PM","activity":"Return to hotel"}],
    "inclusions":["Hotel Pickup & Drop","Tram Ticket","Walking Trail Access"],
    "exclusions":["Food & Drinks","Souvenirs"],
    "rating": 4.8,
    "reviews":[{"name":"Rajesh Kumar","rating":5,"comment":"Amazing night experience with wildlife!"},{"name":"Anna Lee","rating":4,"comment":"Loved the tram ride."}],
    "contactInfo":{"phone":"+65 5566 7788","email":"info@singtours.com"}
  },
  {
    "id": 5,
    "title": "Singapore Zoo and River Safari",
    "slug": "singapore-zoo-river-safari",
    "description": "Enjoy the award-winning Singapore Zoo and River Safari including panda exhibits.",
    "mainImage": "/images/img2.jpg",
    "gallery": ["/images/img1.jpg","/images/img2.jpg","/images/img3.jpg"],
    "duration": "Full Day",
    "price": 90,
    "category": "Wildlife",
    "highlights": ["Singapore Zoo","River Safari","Panda Exhibit"],
    "itinerary":[{"time":"08:30 AM","activity":"Hotel Pickup"},{"time":"09:00 AM","activity":"Singapore Zoo"},{"time":"12:30 PM","activity":"Lunch"},{"time":"01:30 PM","activity":"River Safari"},{"time":"05:00 PM","activity":"Return to hotel"}],
    "inclusions":["Hotel Pickup & Drop","Entry Tickets","Lunch"],
    "exclusions":["Personal Expenses","Souvenirs"],
    "rating": 4.7,
    "reviews":[{"name":"Hannah Tan","rating":5,"comment":"Kids loved the zoo!"},{"name":"David Lim","rating":4,"comment":"Well organized and fun."}],
    "contactInfo":{"phone":"+65 6677 8899","email":"info@singtours.com"}
  },
  {
    "id": 6,
    "title": "Marina Bay Sands SkyPark",
    "slug": "marina-bay-sands-skypak",
    "description": "Enjoy panoramic views from the SkyPark Observation Deck.",
    "mainImage": "/images/img3.jpg",
    "gallery": ["/images/img1.jpg","/images/img2.jpg","/images/img3.jpg"],
    "duration": "Half Day",
    "price": 50,
    "category": "Sightseeing",
    "highlights": ["SkyPark","Infinity Pool View","City Panorama"],
    "itinerary":[{"time":"10:00 AM","activity":"Hotel Pickup"},{"time":"10:30 AM","activity":"SkyPark Visit"},{"time":"12:00 PM","activity":"Return to hotel"}],
    "inclusions":["Entry Ticket","Guide"],
    "exclusions":["Food & Drinks"],
    "rating": 4.6,
    "reviews":[{"name":"Chris Tan","rating":5,"comment":"Amazing views!"},{"name":"Lina Ong","rating":4,"comment":"Worth every penny."}],
    "contactInfo":{"phone":"+65 9988 7766","email":"info@singtours.com"}
  },
  {
    "id": 7,
    "title": "Singapore Flyer Observation",
    "slug": "singapore-flyer",
    "description": "Ride the iconic Singapore Flyer and enjoy the city skyline from above.",
    "mainImage": "/images/img1.jpg",
    "gallery": ["/images/img1.jpg","/images/img2.jpg","/images/img3.jpg"],
    "duration": "1-2 Hours",
    "price": 45,
    "category": "Sightseeing",
    "highlights": ["Panoramic City View","Marina Bay","Gardens by the Bay"],
    "itinerary":[{"time":"11:00 AM","activity":"Hotel Pickup"},{"time":"11:30 AM","activity":"Singapore Flyer Ride"},{"time":"01:00 PM","activity":"Return to hotel"}],
    "inclusions":["Entry Ticket","Guide"],
    "exclusions":["Food & Drinks","Souvenirs"],
    "rating": 4.4,
    "reviews":[{"name":"Kevin Lee","rating":5,"comment":"Breathtaking views from the top."},{"name":"Siti Rahman","rating":4,"comment":"Smooth ride and informative guide."}],
    "contactInfo":{"phone":"+65 7788 5566","email":"info@singtours.com"}
  },
  {
    "id": 8,
    "title": "Chinatown Cultural Walk",
    "slug": "chinatown-walk",
    "description": "Discover Singapore's Chinese heritage through a guided walking tour of Chinatown.",
    "mainImage": "/images/img2.jpg",
    "gallery": ["/images/img1.jpg","/images/img2.jpg","/images/img3.jpg"],
    "duration": "2-3 Hours",
    "price": 30,
    "category": "Cultural",
    "highlights": ["Buddha Tooth Relic Temple","Traditional Shops","Heritage Sites"],
    "itinerary":[{"time":"09:00 AM","activity":"Hotel Pickup"},{"time":"09:30 AM","activity":"Chinatown Walking Tour"},{"time":"12:00 PM","activity":"Return to hotel"}],
    "inclusions":["Guide","Entry Fees"],
    "exclusions":["Meals","Souvenirs"],
    "rating": 4.5,
    "reviews":[{"name":"Maya Tan","rating":5,"comment":"Very informative and fun."},{"name":"Alan Koh","rating":4,"comment":"Learned a lot about local heritage."}],
    "contactInfo":{"phone":"+65 3344 5566","email":"info@singtours.com"}
  },
  {
    "id": 9,
    "title": "Little India Experience",
    "slug": "little-india-experience",
    "description": "Experience the vibrant culture, temples, and food of Little India.",
    "mainImage": "/images/img3.jpg",
    "gallery": ["/images/img1.jpg","/images/img2.jpg","/images/img3.jpg"],
    "duration": "2-3 Hours",
    "price": 35,
    "category": "Cultural",
    "highlights": ["Sri Veeramakaliamman Temple","Street Art","Local Cuisine Tasting"],
    "itinerary":[{"time":"10:00 AM","activity":"Hotel Pickup"},{"time":"10:30 AM","activity":"Little India Tour"},{"time":"01:00 PM","activity":"Return to hotel"}],
    "inclusions":["Guide","Food Tasting","Temple Entry"],
    "exclusions":["Souvenirs","Transport"],
    "rating": 4.6,
    "reviews":[{"name":"Priya Singh","rating":5,"comment":"Colorful and lively experience."},{"name":"Raj Kumar","rating":4,"comment":"Good cultural insight."}],
    "contactInfo":{"phone":"+65 4433 2211","email":"info@singtours.com"}
  },
  {
    "id": 10,
    "title": "Jewel Changi Airport Visit",
    "slug": "jewel-changi-visit",
    "description": "Explore the iconic Jewel at Changi Airport, Rain Vortex, and Canopy Park.",
    "mainImage": "/images/img1.jpg",
    "gallery": ["/images/img1.jpg","/images/img2.jpg","/images/img3.jpg"],
    "duration": "Half Day",
    "price": 40,
    "category": "Sightseeing",
    "highlights": ["Rain Vortex","Canopy Park","Shops & Dining"],
    "itinerary":[{"time":"09:00 AM","activity":"Hotel Pickup"},{"time":"09:30 AM","activity":"Jewel Changi Visit"},{"time":"12:00 PM","activity":"Return to hotel"}],
    "inclusions":["Guide","Entry Ticket"],
    "exclusions":["Food & Drinks","Shopping"],
    "rating": 4.7,
    "reviews":[{"name":"Sophie Tan","rating":5,"comment":"Spectacular waterfall!"},{"name":"Mark Lee","rating":4,"comment":"Lots of attractions to enjoy."}],
    "contactInfo":{"phone":"+65 2233 4455","email":"info@singtours.com"}
  },
  {
    "id": 11,
    "title": "Pulau Ubin Cycling Tour",
    "slug": "pulau-ubin-cycling",
    "description": "Experience the rustic charm of Pulau Ubin on a cycling tour.",
    "mainImage": "/images/img2.jpg",
    "gallery": ["/images/img1.jpg","/images/img2.jpg","/images/img3.jpg"],
    "duration": "Half Day",
    "price": 55,
    "category": "Adventure",
    "highlights": ["Cycling Trails","Traditional Kampung","Nature Spotting"],
    "itinerary":[{"time":"08:30 AM","activity":"Hotel Pickup"},{"time":"09:00 AM","activity":"Ferry to Pulau Ubin"},{"time":"09:30 AM","activity":"Cycling Tour"},{"time":"01:00 PM","activity":"Return to hotel"}],
    "inclusions":["Bike Rental","Guide","Ferry Ticket"],
    "exclusions":["Food & Drinks","Personal Expenses"],
    "rating": 4.6,
    "reviews":[{"name":"Tommy Lim","rating":5,"comment":"Loved cycling around the island!"},{"name":"Rachel Ong","rating":4,"comment":"Relaxing and scenic tour."}],
    "contactInfo":{"phone":"+65 6655 3322","email":"info@singtours.com"}
  },
  {
    "id": 12,
    "title": "Haw Par Villa Cultural Park",
    "slug": "haw-par-villa",
    "description": "Explore the quirky cultural park filled with Chinese mythology statues and exhibits.",
    "mainImage": "/images/img3.jpg",
    "gallery": ["/images/img1.jpg","/images/img2.jpg","/images/img3.jpg"],
    "duration": "2-3 Hours",
    "price": 25,
    "category": "Cultural",
    "highlights": ["Mythology Statues","Tiger Balm Garden","Cultural Exhibits"],
    "itinerary":[{"time":"10:00 AM","activity":"Hotel Pickup"},{"time":"10:30 AM","activity":"Haw Par Villa Tour"},{"time":"01:00 PM","activity":"Return to hotel"}],
    "inclusions":["Guide","Entry Ticket"],
    "exclusions":["Food & Drinks","Souvenirs"],
    "rating": 4.4,
    "reviews":[{"name":"Lee Ming","rating":5,"comment":"Very unique cultural experience!"},{"name":"Ng Wei","rating":4,"comment":"Interesting and fun."}],
    "contactInfo":{"phone":"+65 7788 8899","email":"info@singtours.com"}
  }
]
